niemafs/__init__.py
niemafs/common.py
niemafs/dir.py
niemafs/gcn.py
niemafs/iso.py
niemafs/tar.py
niemafs/wii.py
niemafs/zip.py
niemafs-0.0.15.dist-info/LICENSE
niemafs-0.0.15.dist-info/METADATA
niemafs-0.0.15.dist-info/WHEEL
niemafs-0.0.15.dist-info/top_level.txt
niemafs-0.0.15.dist-info/RECORD
