Metadata-Version: 2.1
Name: niemafs
Version: 0.0.15
Summary: Niema's Python library for reading data from various file system standards
Home-page: https://github.com/niemasd/NiemaFS
Author: Niema Moshiri
Author-email: niemamoshiri@gmail.com
Project-URL: Bug Reports, https://github.com/niemasd/NiemaFS/issues
Project-URL: Source, https://github.com/niemasd/NiemaFS
Keywords: file system filesystem
Classifier: Development Status :: 3 - Alpha
Classifier: Intended Audience :: Developers
Classifier: Topic :: Software Development :: Build Tools
Classifier: License :: OSI Approved :: GNU General Public License v3 or later (GPLv3+)
Classifier: Programming Language :: Python :: 3
Classifier: Programming Language :: Python :: 3.7
Classifier: Programming Language :: Python :: 3.8
Classifier: Programming Language :: Python :: 3.9
Classifier: Programming Language :: Python :: 3.10
Classifier: Programming Language :: Python :: 3.11
License-File: LICENSE
Requires-Dist: pycryptodome
Provides-Extra: dev
Requires-Dist: check-manifest ; extra == 'dev'
